fitrequest/__init__.py
fitrequest/auth.py
fitrequest/aws_var.py
fitrequest/class_factory.py
fitrequest/cli_utils.py
fitrequest/client.py
fitrequest/client_base.py
fitrequest/errors.py
fitrequest/fit_config.py
fitrequest/fit_var.py
fitrequest/generator.py
fitrequest/method_config.py
fitrequest/method_config_family.py
fitrequest/method_config_group.py
fitrequest/method_decorator.py
fitrequest/method_models.py
fitrequest/request_params.py
fitrequest/response.py
fitrequest/response_formatter.py
fitrequest/response_model.py
fitrequest/session.py
fitrequest/templating.py
fitrequest/token_auth.py
fitrequest/utils.py
fitrequest/decorators/__init__.py
fitrequest/decorators/cli_method.py
fitrequest/decorators/fit.py
fitrequest/decorators/hybrid_syntax.py
fitrequest/decorators/paginated.py
fitrequest/decorators/retry.py
fitrequest-1.5.2.dist-info/METADATA
fitrequest-1.5.2.dist-info/WHEEL
fitrequest-1.5.2.dist-info/licenses/LICENSE.md
fitrequest-1.5.2.dist-info/RECORD
