Metadata-Version: 2.4
Name: fitrequest
Version: 1.5.2
Summary: Python class that allow to create REST API client with dynamic code generation
License-File: LICENSE.md
Requires-Python: <3.14,>=3.10
Requires-Dist: aiofiles>=24.1.0
Requires-Dist: boto3>=1.34.96
Requires-Dist: clustershell>=1.9.2
Requires-Dist: defusedxml>=0.7.1
Requires-Dist: httpx>=0.28.1
Requires-Dist: jinja2>=3.1.4
Requires-Dist: jsonpath-ng>=1.7.0
Requires-Dist: makefun>=1.15.4
Requires-Dist: orjson>=3.9.10
Requires-Dist: pydantic-settings>=2.6.1
Requires-Dist: pydantic>=2.5.2
Requires-Dist: rich>=13.9.4
Requires-Dist: strenum>=0.4.15
Requires-Dist: tenacity>=9.0.0
Requires-Dist: typer>=0.15.1
